{"nodes": [{"id": "docker_compose_yaml", "label": "Docker Compose Services", "file_type": "document", "source_file": "docker-compose.yaml", "source_location": null, "source_url": null, "captured_at": null, "author": null, "contributor": null}], "edges": [{"source": "docker_compose_yaml", "target": "config_config_yaml", "relation": "shares_data_with", "confidence": "INFERRED", "confidence_score": 0.75, "source_file": "docker-compose.yaml", "source_location": null, "weight": 0.75}], "hyperedges": []}